README.md
abundance.txt
setup.py
MLmetagenomics/__init__.py
MLmetagenomics/abundance.txt
MLmetagenomics/main.py
MLmetagenomics.egg-info/PKG-INFO
MLmetagenomics.egg-info/SOURCES.txt
MLmetagenomics.egg-info/dependency_links.txt
MLmetagenomics.egg-info/top_level.txt